D47calib/__init__.py
D47calib/_calibs.py
d47calib-1.4.2.dist-info/entry_points.txt
d47calib-1.4.2.dist-info/licenses/LICENSE
d47calib-1.4.2.dist-info/WHEEL
d47calib-1.4.2.dist-info/METADATA
d47calib-1.4.2.dist-info/RECORD
