Metadata-Version: 2.4
Name: D47calib
Version: 1.4.2
Summary: Generate, combine, display and apply Δ47 calibrations
Author-email: Mathieu Daëron <daeron@lsce.ipsl.fr>
Requires-Python: >=3.12
Classifier: License :: OSI Approved :: MIT License
License-File: LICENSE
Requires-Dist: ogls>=1.0.1,<2
Requires-Dist: typer>=0.17.4,<0.18
Requires-Dist: rich>=13.9.4,<13.10
Project-URL: Documentation, https://mdaeron.github.io/D47calib
Project-URL: Home, https://github.com/mdaeron/D47calib
